dagline/__init__.py
dagline/__main__.py
dagline/jobs/dag_processor.py
dagline/models/__init__.py
dagline/models/dag.py
dagline/models/dagbag.py
dagline/models/task.py
dagline/models/operators/__init__.py
dagline/models/operators/python.py
dagline/models/operators/winbat.py
dagline/utils/__init__.py
dagline/utils/cli.py
dagline/utils/logging_setup.py
dagline/utils/state.py
dagline/utils/commands/__init__.py
dagline/utils/commands/dag_command.py
dagline-0.1.0.dist-info/METADATA
dagline-0.1.0.dist-info/WHEEL
dagline-0.1.0.dist-info/licenses/LICENSE
dagline-0.1.0.dist-info/RECORD
