Metadata-Version: 2.1
Name: dagline
Version: 0.1.0
Summary: Use Python's multiprocessing module to execute tasks(python functon and windows bat script) of a DAG in parallel
Author-email: Jason Liang <jasonliangyc@qq.com>
License-File: LICENSE
Classifier: License :: OSI Approved :: MIT License
Classifier: Operating System :: Microsoft :: Windows
Classifier: Programming Language :: Python :: 3
Requires-Python: >=3.10
Requires-Dist: pyvis>=0.3.0
